MANIFEST.in
README.md
setup.py
django_registration_withemail.egg-info/PKG-INFO
django_registration_withemail.egg-info/SOURCES.txt
django_registration_withemail.egg-info/dependency_links.txt
django_registration_withemail.egg-info/requires.txt
django_registration_withemail.egg-info/top_level.txt
registration_withemail/__init__.py
registration_withemail/admin.py
registration_withemail/auth_urls.py
registration_withemail/forms.py
registration_withemail/models.py
registration_withemail/signals.py
registration_withemail/test_urls.py
registration_withemail/tests.py
registration_withemail/urls.py
registration_withemail/views.py