Metadata-Version: 1.1
Name: django-registration-withemail
Version: 0.1.1
Summary: This is a simple user-registration application for Django, designed to make allowing user signups as painless as possible.
Home-page: UNKNOWN
Author: Kamagatos
Author-email: kamagatos@gmail.com
License: BSD License
Platform: UNKNOWN
Classifier: Environment :: Web Environment
Classifier: Framework :: Django
Classifier: Intended Audience :: Developers
Classifier: License :: OSI Approved :: BSD License
Classifier: Operating System :: OS Independent
Classifier: Programming Language :: Python
Classifier: Programming Language :: Python :: 2.6
Classifier: Programming Language :: Python :: 2.7
Classifier: Topic :: Internet :: WWW/HTTP
Classifier: Topic :: Internet :: WWW/HTTP :: Dynamic Content
